relic/sga/core/__init__.py
relic/sga/core/cli.py
relic/sga/core/definitions.py
relic/sga/core/errors.py
relic/sga/core/hashtools.py
relic/sga/core/py.typed
relic/sga/core/serialization.py
relic/sga/core/essencefs/__init__.py
relic/sga/core/essencefs/definitions.py
relic/sga/core/essencefs/opener.py
relic_tool_sga_core-2.0.3.dist-info/LICENSE.txt
relic_tool_sga_core-2.0.3.dist-info/METADATA
relic_tool_sga_core-2.0.3.dist-info/WHEEL
relic_tool_sga_core-2.0.3.dist-info/entry_points.txt
relic_tool_sga_core-2.0.3.dist-info/top_level.txt
relic_tool_sga_core-2.0.3.dist-info/RECORD
