Metadata-Version: 2.2
Name: relic-tool-sga-core
Version: 2.0.3
Summary: Core files shared by versioned SGA files.
Author: Marcus Kertesz
Project-URL: Bug Tracker, https://github.com/MAK-Relic-Tool/Issue-Tracker/issues
Project-URL: Homepage, https://github.com/MAK-Relic-Tool/Relic-Tool-SGA-Core
Classifier: Programming Language :: Python :: 3 :: Only
Classifier: Programming Language :: Python :: 3.9
Classifier: Programming Language :: Python :: 3.10
Classifier: Programming Language :: Python :: 3.11
Classifier: Programming Language :: Python :: 3.12
Classifier: Programming Language :: Python :: 3.13
Classifier: Typing :: Typed
Classifier: License :: OSI Approved :: GNU General Public License v3 (GPLv3)
Requires-Python: >=3.9
License-File: LICENSE.txt
Requires-Dist: relic-tool-core>=2.3.0
Requires-Dist: fs>=2.4.16
